README.rst
setup.py
mezzanine_organization.egg-info/PKG-INFO
mezzanine_organization.egg-info/SOURCES.txt
mezzanine_organization.egg-info/dependency_links.txt
mezzanine_organization.egg-info/not-zip-safe
mezzanine_organization.egg-info/requires.txt
mezzanine_organization.egg-info/top_level.txt
organization/__init__.py
organization/urls.py
organization/agenda/__init__.py
organization/agenda/admin.py
organization/agenda/apps.py
organization/agenda/forms.py
organization/agenda/models.py
organization/agenda/translation.py
organization/agenda/urls.py
organization/agenda/views.py
organization/agenda/management/__init__.py
organization/agenda/management/commands/__init__.py
organization/agenda/management/commands/organization-sync-eve-events.py
organization/agenda/management/commands/organization-sync-prestashop-events.py
organization/agenda/migrations/0001_initial.py
organization/agenda/migrations/0002_eventdepartment.py
organization/agenda/migrations/0003_eventlink_eventperson.py
organization/agenda/migrations/0004_eventaudio_eventvideo.py
organization/agenda/migrations/0005_auto_20160928_1858.py
organization/agenda/migrations/0006_auto_20160929_1257.py
organization/agenda/migrations/0007_auto_20160929_1300.py
organization/agenda/migrations/0008_auto_20161005_1455.py
organization/agenda/migrations/0009_auto_20161013_1631.py
organization/agenda/migrations/0010_auto_20161014_0002.py
organization/agenda/migrations/0011_auto_20161018_1804.py
organization/agenda/migrations/0012_auto_20161020_1051.py
organization/agenda/migrations/0013_eventlink_title.py
organization/agenda/migrations/0014_auto_20161021_1319.py
organization/agenda/migrations/0015_auto_20161026_1025.py
organization/agenda/migrations/0016_dynamiccontentevent.py
organization/agenda/migrations/0017_auto_20161104_1812.py
organization/agenda/migrations/0018_auto_20161104_1820.py
organization/agenda/migrations/0019_eventpricedescription.py
organization/agenda/migrations/0020_auto_20161205_1536.py
organization/agenda/migrations/0021_eventblock_login_required.py
organization/agenda/migrations/0022_auto_20170105_1743.py
organization/agenda/migrations/0023_auto_20170214_1643.py
organization/agenda/migrations/0024_eventrank.py
organization/agenda/migrations/0025_auto_20170222_1011.py
